<?xml version="1.0" encoding="utf-8" ?>
<Defs>

<!-- Sheep Milk -->

  <ThingDef ParentName="OrganicProductBase">
    <defName>SheepMilk</defName>
    <label>sheep milk</label>
    <description>Milk from a sheep.</description>
    <graphicData>
      <texPath>Things/Item/Resource/Milk</texPath>
    </graphicData>
    <socialPropernessMatters>true</socialPropernessMatters>
    <statBases>
      <MarketValue>2.5</MarketValue> <!-- Can be used like meat in recipes -->
      <Mass>0.05</Mass>
      <MaxHitPoints>60</MaxHitPoints>
      <Flammability>0.2</Flammability>
      <Nutrition>0.07</Nutrition>
      <FoodPoisonChanceFixedHuman>0.02</FoodPoisonChanceFixedHuman>
    </statBases>
    <comps>
      <li Class="CompProperties_Rottable">
        <daysToRotStart>14</daysToRotStart>
        <rotDestroys>true</rotDestroys>
      </li>
    </comps>
    <ingestible>
      <preferability>RawTasty</preferability>
      <foodType>AnimalProduct, Fluid</foodType>
      <babiesCanIngest>true</babiesCanIngest>
    </ingestible>
    <thingCategories>
      <li>AnimalProductRaw</li>
    </thingCategories>
    <allowedArchonexusCount>80</allowedArchonexusCount>
  </ThingDef>

<!-- Goat Milk -->

  <ThingDef ParentName="OrganicProductBase">
    <defName>GoatMilk</defName>
    <label>goat milk</label>
    <description>Milk from a goat.</description>
    <graphicData>
      <texPath>Things/Item/Resource/Milk</texPath>
    </graphicData>
    <socialPropernessMatters>true</socialPropernessMatters>
    <statBases>
      <MarketValue>3</MarketValue> <!-- Can be used like meat in recipes -->
      <Mass>0.05</Mass>
      <MaxHitPoints>60</MaxHitPoints>
      <Flammability>0.2</Flammability>
      <Nutrition>0.09</Nutrition>
      <FoodPoisonChanceFixedHuman>0.02</FoodPoisonChanceFixedHuman>
    </statBases>
    <comps>
      <li Class="CompProperties_Rottable">
        <daysToRotStart>14</daysToRotStart>
        <rotDestroys>true</rotDestroys>
      </li>
    </comps>
    <ingestible>
      <preferability>RawTasty</preferability>
      <foodType>AnimalProduct, Fluid</foodType>
      <babiesCanIngest>true</babiesCanIngest>
    </ingestible>
    <thingCategories>
      <li>AnimalProductRaw</li>
    </thingCategories>
    <allowedArchonexusCount>80</allowedArchonexusCount>
  </ThingDef>

</Defs>  
